<!--
  #%L
  GwtBootstrap3
  %%
  Copyright (C) 2013 GwtBootstrap3
  %%
  Licensed under the Apache License, Version 2.0 (the "License");
  you may not use this file except in compliance with the License.
  You may obtain a copy of the License at

       http://www.apache.org/licenses/LICENSE-2.0

  Unless required by applicable law or agreed to in writing, software
  distributed under the License is distributed on an "AS IS" BASIS,
  WITHOUT WARRANTIES OR CONDITIONS OF ANY KIND, either express or implied.
  See the License for the specific language governing permissions and
  limitations under the License.
  #L%
  -->
<ui:UiBinder xmlns:ui="urn:ui:com.google.gwt.uibinder"
             xmlns:b="urn:import:org.gwtbootstrap3.client.ui"
             xmlns:b.html="urn:import:org.gwtbootstrap3.client.ui.html"
             xmlns:b3="urn:import:org.gwtbootstrap3.extras.slider.client.ui"
             xmlns:d="urn:import:org.gwtbootstrap3.demo.client.ui">

    <ui:style>
        .danger {
            background-color: #fcf2f2;
            border-color: #dFb5b4;
        }

        .margin-fix {
            margin-top: 0 !important;
        }

        .spacing {
            margin-left: 5px;
        }
    </ui:style>

    <b:Row>
        <b:Column size="XS_12">

            <b:PageHeader text="Slider"/>

            <b:BlockQuote>
                <b.html:Strong>Original Library Link:</b.html:Strong>
                <b:Anchor addStyleNames="{style.spacing}" href="http://seiyria.github.io/bootstrap-slider/">Bootstrap
                    Slider
                </b:Anchor>
                <b.html:Br/>
                <b.html:Strong>Current Version Supported: 4.5.1</b.html:Strong>
            </b:BlockQuote>

            <b:BlockQuote addStyleNames="{style.danger}">
                <b.html:Strong>This extra only support modern browsers. Basically, any browser below IE9 is not compatible.</b.html:Strong>
            </b:BlockQuote>

            <b:BlockQuote addStyleNames="{style.danger}">
                <b:Heading addStyleNames="{style.margin-fix}" size="H4" text="Required for use"/>
                <b.html:Paragraph>
                    To use Slider, you must first add the extras module to your project. In Maven:
                </b.html:Paragraph>
                <d:PrettyPre addStyleNames="lang-xml">
                    &lt;dependency&gt;\n
                    \s\s\s\s&lt;groupId&gt;org.gwtbootstrap3&lt;/groupId&gt;\n
                    \s\s\s\s&lt;artifactId&gt;gwtbootstrap3-extras&lt;/artifactId&gt;\n
                    \s\s\s\s&lt;version&gt;VERSION&lt;/version&gt;\n
                    \s\s\s\s&lt;scope&gt;provided&lt;/scope&gt;\n
                    &lt;/dependency&gt;
                </d:PrettyPre>
                <b.html:Paragraph>
                    Then you need to inherit the following GWT Module
                    <strong>additionally</strong>
                    to any GwtBootstrap3
                    module into your *.gwt.xml of your project:
                </b.html:Paragraph>
                <d:PrettyPre addStyleNames="lang-xml">
                    &lt;inherits name="org.gwtbootstrap3.extras.slider.Slider"/&gt;
                </d:PrettyPre>
                <b.html:Paragraph>
                    Last but not least must add this namespace to your *.ui.xml (don't have to name it b3):
                </b.html:Paragraph>
                <d:PrettyPre addStyleNames="lang-xml">
                    xmlns:b3="urn:import:org.gwtbootstrap3.extras.slider.client.ui"
                </d:PrettyPre>
            </b:BlockQuote>

            <!-- Basic slider -->
            <b:Panel>
                <b:PanelHeader>
                    <b:Heading size="H3" text="Basic Slider"/>
                </b:PanelHeader>
                <b:PanelBody>
                    <b3:Slider min="0" max="20" step="1" value="14"/>
                </b:PanelBody>
                <b:PanelFooter>
                    <d:PrettyPre addStyleNames="lang-xml">
                        &lt;b3:Slider min="0", max="20" step="1" value="14"/&gt;\n
                    </d:PrettyPre>
                </b:PanelFooter>
            </b:Panel>

            <!-- Range slider -->
            <b:Panel>
                <b:PanelHeader>
                    <b:Heading size="H3" text="Range Slider"/>
                </b:PanelHeader>
                <b:PanelBody>
                    <b.html:Strong text="€ 10"/>
                    <b3:RangeSlider min="10" max="1000" step="5" value="[250,450]"/>
                    <b.html:Strong text="€ 1000"/>
                </b:PanelBody>
                <b:PanelFooter>
                    <d:PrettyPre addStyleNames="lang-xml">
                        &lt;b3:RangeSlider min="10" max="1000" step="5" value="[250,450]"/&gt;\n
                    </d:PrettyPre>
                </b:PanelFooter>
            </b:Panel>

            <!-- Formatter -->
            <b:Panel>
                <b:PanelHeader>
                    <b:Heading size="H3" text="Formatter"/>
                </b:PanelHeader>
                <b:PanelBody>
                    <b3:Slider ui:field="formatterExample" min="-100.0" max="100.0" value="0" step="5.0"/>
                </b:PanelBody>
                <b:PanelFooter>
                    <d:PrettyPre addStyleNames="lang-xml">
                        &lt;b3:Slider ui:field=“mySliedr” min="-100.0" max="100.0" value="0" step="5.0"/&gt;\n
                    </d:PrettyPre>
                    <d:PrettyPre addStyleNames="lang-java">
                        mySliedr.setFormatter(new FormatterCallback() {\n
                        \s\s@Override\n
                        \s\spublic String formatTooltip(final double value) {\n
                        \s\s\sreturn "Current value: " + value;\n
                        \s\s}\n
                        });\n
                    </d:PrettyPre>
                </b:PanelFooter>
            </b:Panel>

            <!-- FIXME: Vertical slider is broken, to be enabled in later version -->
            <b:Panel visible="false">
                <b:PanelHeader>
                    <b:Heading size="H3" text="Vertical Slider"/>
                </b:PanelHeader>
                <b:PanelBody>
                    <b3:Slider min="0" max="10" value="5" orientation="VERTICAL"/>
                </b:PanelBody>
                <b:PanelFooter>
                    <d:PrettyPre addStyleNames="lang-xml">
                        &lt;b3:Slider orientation="VERTICAL"/&gt;\n
                    </d:PrettyPre>
                </b:PanelFooter>
            </b:Panel>
        </b:Column>
    </b:Row>

</ui:UiBinder>
